scodakit/__init__.py
scodakit/download.py
scodakit/main.py
scodakit/map_generator.py
scodakit/merge_catalogue.py
scodakit/picking.py
scodakit/plots.py
scodakit/process.py
scodakit/utils.py
scodakit-1.0.0.dist-info/licenses/License.md
scodakit-1.0.0.dist-info/METADATA
scodakit-1.0.0.dist-info/WHEEL
scodakit-1.0.0.dist-info/entry_points.txt
scodakit-1.0.0.dist-info/top_level.txt
scodakit-1.0.0.dist-info/RECORD
