Metadata-Version: 2.4
Name: scodakit
Version: 1.0.0
Summary: ScodaKit: A scientific Python-based command line toolkit for S-coda seismic wave analysis and scattering parameters estimation
Author-email: Marios Karagiorgas <karagiorgasmarios@gmail.com>
Maintainer-email: Marios Karagiorgas <karagiorgasmarios@gmail.com>
License: Apache License
Project-URL: Homepage, https://github.com/marioskaragiorgas/ScodaKit
Project-URL: Documentation, https://github.com/marioskaragiorgas/ScodaKit#readme
Project-URL: Issues, https://github.com/marioskaragiorgas/ScodaKit/issues
Keywords: geophysics,seismology, S-coda waves,mean free path,coda attenuation factor,earthquake, seismic wave scattering
Classifier: Development Status :: 4 - Beta
Classifier: Intended Audience :: Science/Research
Classifier: Topic :: Scientific/Engineering :: Information Analysis
Classifier: Topic :: Scientific/Engineering :: Physics
Classifier: Programming Language :: Python :: 3
Classifier: License :: OSI Approved :: Apache Software License
Classifier: Operating System :: OS Independent
Requires-Python: >=3.7
License-File: License.md
Requires-Dist: numpy
Requires-Dist: scipy
Requires-Dist: obspy
Requires-Dist: pandas
Requires-Dist: matplotlib
Requires-Dist: scikit-learn
Requires-Dist: cartopy
Requires-Dist: geopandas
Requires-Dist: openpyxl
Dynamic: license-file
